CONTRIBUTING.md
py2puml/__init__.py
py2puml/__main__.py
py2puml/asserts.py
py2puml/cli.py
py2puml/domain/__init__.py
py2puml/domain/umlclass.py
py2puml/domain/umlenum.py
py2puml/domain/umlitem.py
py2puml/domain/umlrelation.py
py2puml/export/puml.py
py2puml/inspection/__init__.py
py2puml/inspection/inspectclass.py
py2puml/inspection/inspectenum.py
py2puml/inspection/inspectmodule.py
py2puml/inspection/inspectnamedtuple.py
py2puml/inspection/inspectpackage.py
py2puml/parsing/__init__.py
py2puml/parsing/astvisitors.py
py2puml/parsing/compoundtypesplitter.py
py2puml/parsing/moduleresolver.py
py2puml/parsing/parseclassconstructor.py
py2puml/py2puml.domain.puml
py2puml/py2puml.py
py2puml/utils.py
py2puml-0.9.0.dist-info/LICENSE
py2puml-0.9.0.dist-info/METADATA
py2puml-0.9.0.dist-info/WHEEL
py2puml-0.9.0.dist-info/entry_points.txt
py2puml-0.9.0.dist-info/RECORD
