Metadata-Version: 2.1
Name: py2puml
Version: 0.9.0
Summary: Generate PlantUML class diagrams to document your Python application.
Home-page: https://github.com/lucsorel/py2puml
License: MIT
Keywords: class diagram,PlantUML,documentation,inspection,AST
Author: Luc Sorel-Giffo
Maintainer: Luc Sorel-Giffo
Requires-Python: >=3.8,<4.0
Classifier: License :: OSI Approved :: MIT License
Classifier: Programming Language :: Python :: 3
Classifier: Programming Language :: Python :: 3.8
Classifier: Programming Language :: Python :: 3.9
Classifier: Programming Language :: Python :: 3.10
Classifier: Programming Language :: Python :: 3.11
Project-URL: Repository, https://github.com/lucsorel/py2puml
